{
  "cdid": "NRLR",
  "note1": "This content is not available in the prototype but in future will provide a note about this timeseries.",
  "note2": "This content is not available in the prototype but in future will provide a note about this timeseries.",
  "unit": "",
  "source": "Office for National Statistics",
  "nationalStatistic": false,
  "years": [
    {
      "date": "1987",
      "value": "51950",
      "year": "1987",
      "sourceDataset": "BB"
    },
    {
      "date": "1988",
      "value": "66401",
      "year": "1988",
      "sourceDataset": "BB"
    },
    {
      "date": "1989",
      "value": "77071",
      "year": "1989",
      "sourceDataset": "BB"
    },
    {
      "date": "1990",
      "value": "76700",
      "year": "1990",
      "sourceDataset": "BB"
    },
    {
      "date": "1991",
      "value": "74388",
      "year": "1991",
      "sourceDataset": "BB"
    },
    {
      "date": "1992",
      "value": "57491",
      "year": "1992",
      "sourceDataset": "BB"
    },
    {
      "date": "1993",
      "value": "48559",
      "year": "1993",
      "sourceDataset": "BB"
    },
    {
      "date": "1994",
      "value": "56389",
      "year": "1994",
      "sourceDataset": "BB"
    },
    {
      "date": "1995",
      "value": "65736",
      "year": "1995",
      "sourceDataset": "BB"
    },
    {
      "date": "1996",
      "value": "75125",
      "year": "1996",
      "sourceDataset": "BB"
    },
    {
      "date": "1997",
      "value": "88588",
      "year": "1997",
      "sourceDataset": "BB"
    },
    {
      "date": "1998",
      "value": "109629",
      "year": "1998",
      "sourceDataset": "BB"
    },
    {
      "date": "1999",
      "value": "125492",
      "year": "1999",
      "sourceDataset": "BB"
    },
    {
      "date": "2000",
      "value": "137838",
      "year": "2000",
      "sourceDataset": "BB"
    },
    {
      "date": "2001",
      "value": "141037",
      "year": "2001",
      "sourceDataset": "BB"
    },
    {
      "date": "2002",
      "value": "127666",
      "year": "2002",
      "sourceDataset": "BB"
    },
    {
      "date": "2003",
      "value": "125708",
      "year": "2003",
      "sourceDataset": "BB"
    },
    {
      "date": "2004",
      "value": "135133",
      "year": "2004",
      "sourceDataset": "BB"
    },
    {
      "date": "2005",
      "value": "145341",
      "year": "2005",
      "sourceDataset": "BB"
    },
    {
      "date": "2006",
      "value": "163567",
      "year": "2006",
      "sourceDataset": "BB"
    },
    {
      "date": "2007",
      "value": "167314",
      "year": "2007",
      "sourceDataset": "BB"
    },
    {
      "date": "2008",
      "value": "164732",
      "year": "2008",
      "sourceDataset": "BB"
    },
    {
      "date": "2009",
      "value": "105777",
      "year": "2009",
      "sourceDataset": "BB"
    },
    {
      "date": "2010",
      "value": "101613",
      "year": "2010",
      "sourceDataset": "BB"
    },
    {
      "date": "2011",
      "value": "126306",
      "year": "2011",
      "sourceDataset": "BB"
    },
    {
      "date": "2012",
      "value": "123039",
      "year": "2012",
      "sourceDataset": "BB"
    },
    {
      "date": "2013",
      "value": "169826",
      "year": "2013",
      "sourceDataset": "UKEA"
    }
  ],
  "quarters": [
    {
      "date": "1997 Q1",
      "value": "24486",
      "year": "1997",
      "quarter": "Q1",
      "sourceDataset": "UKEA"
    },
    {
      "date": "1997 Q2",
      "value": "15443",
      "year": "1997",
      "quarter": "Q2",
      "sourceDataset": "UKEA"
    },
    {
      "date": "1997 Q3",
      "value": "21645",
      "year": "1997",
      "quarter": "Q3",
      "sourceDataset": "UKEA"
    },
    {
      "date": "1997 Q4",
      "value": "30556",
      "year": "1997",
      "quarter": "Q4",
      "sourceDataset": "UKEA"
    },
    {
      "date": "1998 Q1",
      "value": "34472",
      "year": "1998",
      "quarter": "Q1",
      "sourceDataset": "UKEA"
    },
    {
      "date": "1998 Q2",
      "value": "18171",
      "year": "1998",
      "quarter": "Q2",
      "sourceDataset": "UKEA"
    },
    {
      "date": "1998 Q3",
      "value": "27881",
      "year": "1998",
      "quarter": "Q3",
      "sourceDataset": "UKEA"
    },
    {
      "date": "1998 Q4",
      "value": "32894",
      "year": "1998",
      "quarter": "Q4",
      "sourceDataset": "UKEA"
    },
    {
      "date": "1999 Q1",
      "value": "38896",
      "year": "1999",
      "quarter": "Q1",
      "sourceDataset": "UKEA"
    },
    {
      "date": "1999 Q2",
      "value": "23475",
      "year": "1999",
      "quarter": "Q2",
      "sourceDataset": "UKEA"
    },
    {
      "date": "1999 Q3",
      "value": "33484",
      "year": "1999",
      "quarter": "Q3",
      "sourceDataset": "UKEA"
    },
    {
      "date": "1999 Q4",
      "value": "33640",
      "year": "1999",
      "quarter": "Q4",
      "sourceDataset": "UKEA"
    },
    {
      "date": "2000 Q1",
      "value": "44718",
      "year": "2000",
      "quarter": "Q1",
      "sourceDataset": "UKEA"
    },
    {
      "date": "2000 Q2",
      "value": "27969",
      "year": "2000",
      "quarter": "Q2",
      "sourceDataset": "UKEA"
    },
    {
      "date": "2000 Q3",
      "value": "35381",
      "year": "2000",
      "quarter": "Q3",
      "sourceDataset": "UKEA"
    },
    {
      "date": "2000 Q4",
      "value": "34089",
      "year": "2000",
      "quarter": "Q4",
      "sourceDataset": "UKEA"
    },
    {
      "date": "2001 Q1",
      "value": "48455",
      "year": "2001",
      "quarter": "Q1",
      "sourceDataset": "UKEA"
    },
    {
      "date": "2001 Q2",
      "value": "27177",
      "year": "2001",
      "quarter": "Q2",
      "sourceDataset": "UKEA"
    },
    {
      "date": "2001 Q3",
      "value": "37584",
      "year": "2001",
      "quarter": "Q3",
      "sourceDataset": "UKEA"
    },
    {
      "date": "2001 Q4",
      "value": "32166",
      "year": "2001",
      "quarter": "Q4",
      "sourceDataset": "UKEA"
    },
    {
      "date": "2002 Q1",
      "value": "44184",
      "year": "2002",
      "quarter": "Q1",
      "sourceDataset": "UKEA"
    },
    {
      "date": "2002 Q2",
      "value": "25248",
      "year": "2002",
      "quarter": "Q2",
      "sourceDataset": "UKEA"
    },
    {
      "date": "2002 Q3",
      "value": "34450",
      "year": "2002",
      "quarter": "Q3",
      "sourceDataset": "UKEA"
    },
    {
      "date": "2002 Q4",
      "value": "28874",
      "year": "2002",
      "quarter": "Q4",
      "sourceDataset": "UKEA"
    },
    {
      "date": "2003 Q1",
      "value": "43758",
      "year": "2003",
      "quarter": "Q1",
      "sourceDataset": "UKEA"
    },
    {
      "date": "2003 Q2",
      "value": "25003",
      "year": "2003",
      "quarter": "Q2",
      "sourceDataset": "UKEA"
    },
    {
      "date": "2003 Q3",
      "value": "34232",
      "year": "2003",
      "quarter": "Q3",
      "sourceDataset": "UKEA"
    },
    {
      "date": "2003 Q4",
      "value": "28580",
      "year": "2003",
      "quarter": "Q4",
      "sourceDataset": "UKEA"
    },
    {
      "date": "2004 Q1",
      "value": "47402",
      "year": "2004",
      "quarter": "Q1",
      "sourceDataset": "UKEA"
    },
    {
      "date": "2004 Q2",
      "value": "26517",
      "year": "2004",
      "quarter": "Q2",
      "sourceDataset": "UKEA"
    },
    {
      "date": "2004 Q3",
      "value": "35228",
      "year": "2004",
      "quarter": "Q3",
      "sourceDataset": "UKEA"
    },
    {
      "date": "2004 Q4",
      "value": "31924",
      "year": "2004",
      "quarter": "Q4",
      "sourceDataset": "UKEA"
    },
    {
      "date": "2005 Q1",
      "value": "50220",
      "year": "2005",
      "quarter": "Q1",
      "sourceDataset": "UKEA"
    },
    {
      "date": "2005 Q2",
      "value": "29249",
      "year": "2005",
      "quarter": "Q2",
      "sourceDataset": "UKEA"
    },
    {
      "date": "2005 Q3",
      "value": "40206",
      "year": "2005",
      "quarter": "Q3",
      "sourceDataset": "UKEA"
    },
    {
      "date": "2005 Q4",
      "value": "32327",
      "year": "2005",
      "quarter": "Q4",
      "sourceDataset": "UKEA"
    },
    {
      "date": "2006 Q1",
      "value": "58230",
      "year": "2006",
      "quarter": "Q1",
      "sourceDataset": "UKEA"
    },
    {
      "date": "2006 Q2",
      "value": "27820",
      "year": "2006",
      "quarter": "Q2",
      "sourceDataset": "UKEA"
    },
    {
      "date": "2006 Q3",
      "value": "44879",
      "year": "2006",
      "quarter": "Q3",
      "sourceDataset": "UKEA"
    },
    {
      "date": "2006 Q4",
      "value": "39563",
      "year": "2006",
      "quarter": "Q4",
      "sourceDataset": "UKEA"
    },
    {
      "date": "2007 Q1",
      "value": "62968",
      "year": "2007",
      "quarter": "Q1",
      "sourceDataset": "UKEA"
    },
    {
      "date": "2007 Q2",
      "value": "29474",
      "year": "2007",
      "quarter": "Q2",
      "sourceDataset": "UKEA"
    },
    {
      "date": "2007 Q3",
      "value": "45334",
      "year": "2007",
      "quarter": "Q3",
      "sourceDataset": "UKEA"
    },
    {
      "date": "2007 Q4",
      "value": "37141",
      "year": "2007",
      "quarter": "Q4",
      "sourceDataset": "UKEA"
    },
    {
      "date": "2008 Q1",
      "value": "70453",
      "year": "2008",
      "quarter": "Q1",
      "sourceDataset": "UKEA"
    },
    {
      "date": "2008 Q2",
      "value": "28023",
      "year": "2008",
      "quarter": "Q2",
      "sourceDataset": "UKEA"
    },
    {
      "date": "2008 Q3",
      "value": "44414",
      "year": "2008",
      "quarter": "Q3",
      "sourceDataset": "UKEA"
    },
    {
      "date": "2008 Q4",
      "value": "30294",
      "year": "2008",
      "quarter": "Q4",
      "sourceDataset": "UKEA"
    },
    {
      "date": "2009 Q1",
      "value": "51894",
      "year": "2009",
      "quarter": "Q1",
      "sourceDataset": "UKEA"
    },
    {
      "date": "2009 Q2",
      "value": "11957",
      "year": "2009",
      "quarter": "Q2",
      "sourceDataset": "UKEA"
    },
    {
      "date": "2009 Q3",
      "value": "29871",
      "year": "2009",
      "quarter": "Q3",
      "sourceDataset": "UKEA"
    },
    {
      "date": "2009 Q4",
      "value": "20832",
      "year": "2009",
      "quarter": "Q4",
      "sourceDataset": "UKEA"
    },
    {
      "date": "2010 Q1",
      "value": "47591",
      "year": "2010",
      "quarter": "Q1",
      "sourceDataset": "UKEA"
    },
    {
      "date": "2010 Q2",
      "value": "15274",
      "year": "2010",
      "quarter": "Q2",
      "sourceDataset": "UKEA"
    },
    {
      "date": "2010 Q3",
      "value": "29888",
      "year": "2010",
      "quarter": "Q3",
      "sourceDataset": "UKEA"
    },
    {
      "date": "2010 Q4",
      "value": "19341",
      "year": "2010",
      "quarter": "Q4",
      "sourceDataset": "UKEA"
    },
    {
      "date": "2011 Q1",
      "value": "56144",
      "year": "2011",
      "quarter": "Q1",
      "sourceDataset": "UKEA"
    },
    {
      "date": "2011 Q2",
      "value": "14884",
      "year": "2011",
      "quarter": "Q2",
      "sourceDataset": "UKEA"
    },
    {
      "date": "2011 Q3",
      "value": "37993",
      "year": "2011",
      "quarter": "Q3",
      "sourceDataset": "UKEA"
    },
    {
      "date": "2011 Q4",
      "value": "29075",
      "year": "2011",
      "quarter": "Q4",
      "sourceDataset": "UKEA"
    },
    {
      "date": "2012 Q1",
      "value": "55511",
      "year": "2012",
      "quarter": "Q1",
      "sourceDataset": "UKEA"
    },
    {
      "date": "2012 Q2",
      "value": "19712",
      "year": "2012",
      "quarter": "Q2",
      "sourceDataset": "UKEA"
    },
    {
      "date": "2012 Q3",
      "value": "35480",
      "year": "2012",
      "quarter": "Q3",
      "sourceDataset": "UKEA"
    },
    {
      "date": "2012 Q4",
      "value": "26185",
      "year": "2012",
      "quarter": "Q4",
      "sourceDataset": "UKEA"
    },
    {
      "date": "2013 Q1",
      "value": "63491",
      "year": "2013",
      "quarter": "Q1",
      "sourceDataset": "UKEA"
    },
    {
      "date": "2013 Q2",
      "value": "29241",
      "year": "2013",
      "quarter": "Q2",
      "sourceDataset": "UKEA"
    },
    {
      "date": "2013 Q3",
      "value": "42707",
      "year": "2013",
      "quarter": "Q3",
      "sourceDataset": "UKEA"
    },
    {
      "date": "2013 Q4",
      "value": "34387",
      "year": "2013",
      "quarter": "Q4",
      "sourceDataset": "UKEA"
    },
    {
      "date": "2014 Q1",
      "value": "60030",
      "year": "2014",
      "quarter": "Q1",
      "sourceDataset": "UKEA"
    },
    {
      "date": "2014 Q2",
      "value": "25566",
      "year": "2014",
      "quarter": "Q2",
      "sourceDataset": "UKEA"
    }
  ],
  "months": [],
  "relatedBulletins": [
    "/economy/nationalaccounts/bulletins/balanceofpaymentsq12014"
  ],
  "relatedTimeseries": [],
  "sourceDatasets": [
    "BB",
    "UKEA"
  ],
  "type": "timeseries",
  "name": "Secondary distribution of income account: Gross disposable income: CP NSA",
  "uri": "/economy/nationalaccounts/timeseries/nrlr",
  "fileName": "nrlr",
  "breadcrumb": [
    {
      "index": 0,
      "type": "home",
      "name": "Economy",
      "fileName": "economy"
    },
    {
      "index": 0,
      "type": "home",
      "name": "National Accounts",
      "fileName": "nationalaccounts",
      "breadcrumb": []
    }
  ]
}