{
  "cdid": "L5ZH",
  "note1": "Lorem ipsum dolor sit amet, consectetur adipiscing elit. Praesent quam leo, blandit a turpis non, varius feugiat mi. Lorem ipsum dolor sit amet, consectetur adipiscing elit. In posuere lectus eu laoreet ultrices. Donec ac sodales libero, eget fermentum arcu.",
  "note2": "Fusce pharetra, libero in imperdiet ultricies, ex erat tempor dolor, vitae aliquet magna velit in urna. Duis finibus augue velit, ut consectetur risus imperdiet in. Sed tempus congue ante, ac cursus diam porttitor vitae. Vivamus arcu leo, volutpat in mauris ac, lacinia fermentum velit. Sed dictum tortor justo, aliquet facilisis lorem dictum a.",
  "data": [
    {
      "date": "1987",
      "value": "233"
    },
    {
      "date": "1988",
      "value": "249"
    },
    {
      "date": "1989",
      "value": "714"
    },
    {
      "date": "1990",
      "value": "870"
    },
    {
      "date": "1991",
      "value": "860"
    },
    {
      "date": "1992",
      "value": "896"
    },
    {
      "date": "1993",
      "value": "905"
    },
    {
      "date": "1994",
      "value": "950"
    },
    {
      "date": "1995",
      "value": "962"
    },
    {
      "date": "1996",
      "value": "1199"
    },
    {
      "date": "1997",
      "value": "1412"
    },
    {
      "date": "1998",
      "value": "1559"
    },
    {
      "date": "1999",
      "value": "1626"
    },
    {
      "date": "2000",
      "value": "1954"
    },
    {
      "date": "2001",
      "value": "2117"
    },
    {
      "date": "2002",
      "value": "2708"
    },
    {
      "date": "2003",
      "value": "4531"
    },
    {
      "date": "2004",
      "value": "3613"
    },
    {
      "date": "2005",
      "value": "4181"
    },
    {
      "date": "2006",
      "value": "2796"
    },
    {
      "date": "2007",
      "value": "4328"
    },
    {
      "date": "2008",
      "value": "4302"
    },
    {
      "date": "2009",
      "value": "3246"
    },
    {
      "date": "2010",
      "value": "3693"
    },
    {
      "date": "2011",
      "value": "3752"
    },
    {
      "date": "2012",
      "value": "3539"
    }
  ],
  "uri": "/economy/nationalaccounts/timeseries/l5zh",
  "type": "timeseries",
  "name": "GFCF:Financial corporations: TOTAL: Intangible fixed assets: £m: CP: NSA",
  "fileName": "l5zh",
  "breadcrumb": [
    {
      "index": 0,
      "type": "home",
      "name": "Economy",
      "fileName": "economy"
    },
    {
      "index": 0,
      "type": "home",
      "name": "National Accounts",
      "fileName": "nationalaccounts",
      "breadcrumb": []
    }
  ]
}