{
  "cdid": "P38N",
  "note1": "Lorem ipsum dolor sit amet, consectetur adipiscing elit. Praesent quam leo, blandit a turpis non, varius feugiat mi. Lorem ipsum dolor sit amet, consectetur adipiscing elit. In posuere lectus eu laoreet ultrices. Donec ac sodales libero, eget fermentum arcu.",
  "note2": "Fusce pharetra, libero in imperdiet ultricies, ex erat tempor dolor, vitae aliquet magna velit in urna. Duis finibus augue velit, ut consectetur risus imperdiet in. Sed tempus congue ante, ac cursus diam porttitor vitae. Vivamus arcu leo, volutpat in mauris ac, lacinia fermentum velit. Sed dictum tortor justo, aliquet facilisis lorem dictum a.",
  "data": [
    {
      "date": "1998",
      "value": "991"
    },
    {
      "date": "1999",
      "value": "1140"
    },
    {
      "date": "2000",
      "value": "1731"
    },
    {
      "date": "2001",
      "value": "1953"
    },
    {
      "date": "2002",
      "value": "2578"
    },
    {
      "date": "2003",
      "value": "3033"
    },
    {
      "date": "2004",
      "value": "3253"
    },
    {
      "date": "2005",
      "value": "3466"
    },
    {
      "date": "2006",
      "value": "3754"
    },
    {
      "date": "2007",
      "value": "3911"
    },
    {
      "date": "2008",
      "value": "3783"
    },
    {
      "date": "2009",
      "value": "3618"
    },
    {
      "date": "2010",
      "value": "3713"
    },
    {
      "date": "2011",
      "value": "4067"
    },
    {
      "date": "2012",
      "value": "4194"
    },
    {
      "date": "2013",
      "value": "4465"
    },
    {
      "date": "1998 Q1",
      "value": "250"
    },
    {
      "date": "1998 Q2",
      "value": "274"
    },
    {
      "date": "1998 Q3",
      "value": "241"
    },
    {
      "date": "1998 Q4",
      "value": "226"
    },
    {
      "date": "1999 Q1",
      "value": "306"
    },
    {
      "date": "1999 Q2",
      "value": "274"
    },
    {
      "date": "1999 Q3",
      "value": "219"
    },
    {
      "date": "1999 Q4",
      "value": "341"
    },
    {
      "date": "2000 Q1",
      "value": "432"
    },
    {
      "date": "2000 Q2",
      "value": "406"
    },
    {
      "date": "2000 Q3",
      "value": "453"
    },
    {
      "date": "2000 Q4",
      "value": "440"
    },
    {
      "date": "2001 Q1",
      "value": "516"
    },
    {
      "date": "2001 Q2",
      "value": "459"
    },
    {
      "date": "2001 Q3",
      "value": "473"
    },
    {
      "date": "2001 Q4",
      "value": "505"
    },
    {
      "date": "2002 Q1",
      "value": "579"
    },
    {
      "date": "2002 Q2",
      "value": "652"
    },
    {
      "date": "2002 Q3",
      "value": "666"
    },
    {
      "date": "2002 Q4",
      "value": "681"
    },
    {
      "date": "2003 Q1",
      "value": "820"
    },
    {
      "date": "2003 Q2",
      "value": "721"
    },
    {
      "date": "2003 Q3",
      "value": "726"
    },
    {
      "date": "2003 Q4",
      "value": "766"
    },
    {
      "date": "2004 Q1",
      "value": "786"
    },
    {
      "date": "2004 Q2",
      "value": "810"
    },
    {
      "date": "2004 Q3",
      "value": "823"
    },
    {
      "date": "2004 Q4",
      "value": "834"
    },
    {
      "date": "2005 Q1",
      "value": "823"
    },
    {
      "date": "2005 Q2",
      "value": "901"
    },
    {
      "date": "2005 Q3",
      "value": "879"
    },
    {
      "date": "2005 Q4",
      "value": "863"
    },
    {
      "date": "2006 Q1",
      "value": "937"
    },
    {
      "date": "2006 Q2",
      "value": "904"
    },
    {
      "date": "2006 Q3",
      "value": "933"
    },
    {
      "date": "2006 Q4",
      "value": "980"
    },
    {
      "date": "2007 Q1",
      "value": "996"
    },
    {
      "date": "2007 Q2",
      "value": "966"
    },
    {
      "date": "2007 Q3",
      "value": "987"
    },
    {
      "date": "2007 Q4",
      "value": "962"
    },
    {
      "date": "2008 Q1",
      "value": "888"
    },
    {
      "date": "2008 Q2",
      "value": "1014"
    },
    {
      "date": "2008 Q3",
      "value": "967"
    },
    {
      "date": "2008 Q4",
      "value": "914"
    },
    {
      "date": "2009 Q1",
      "value": "888"
    },
    {
      "date": "2009 Q2",
      "value": "875"
    },
    {
      "date": "2009 Q3",
      "value": "918"
    },
    {
      "date": "2009 Q4",
      "value": "937"
    },
    {
      "date": "2010 Q1",
      "value": "950"
    },
    {
      "date": "2010 Q2",
      "value": "932"
    },
    {
      "date": "2010 Q3",
      "value": "904"
    },
    {
      "date": "2010 Q4",
      "value": "927"
    },
    {
      "date": "2011 Q1",
      "value": "1018"
    },
    {
      "date": "2011 Q2",
      "value": "993"
    },
    {
      "date": "2011 Q3",
      "value": "1018"
    },
    {
      "date": "2011 Q4",
      "value": "1038"
    },
    {
      "date": "2012 Q1",
      "value": "1026"
    },
    {
      "date": "2012 Q2",
      "value": "1031"
    },
    {
      "date": "2012 Q3",
      "value": "1035"
    },
    {
      "date": "2012 Q4",
      "value": "1102"
    },
    {
      "date": "2013 Q1",
      "value": "1084"
    },
    {
      "date": "2013 Q2",
      "value": "1146"
    },
    {
      "date": "2013 Q3",
      "value": "1127"
    },
    {
      "date": "2013 Q4",
      "value": "1108"
    },
    {
      "date": "2014 Q1",
      "value": "1110"
    },
    {
      "date": "2014 Q2",
      "value": "1146"
    }
  ],
  "uri": "/businessindustryandtrade/internationaltrade/timeseries/p38n",
  "type": "timeseries",
  "name": "CPA 08:WW:EX:CVM:BOP:SA: 20.4. Cleaning \u0026 polishing prep, perfumes \u0026 toilet pre",
  "fileName": "p38n",
  "breadcrumb": [
    {
      "index": 0,
      "type": "home",
      "name": "Business, Industry and Trade",
      "fileName": "businessindustryandtrade"
    },
    {
      "index": 0,
      "type": "home",
      "name": "International Trade",
      "fileName": "internationaltrade",
      "breadcrumb": []
    }
  ]
}