{
  "cdid": "L8NI",
  "note1": "This content is not available in the prototype but in future will provide a note about this timeseries.",
  "note2": "This content is not available in the prototype but in future will provide a note about this timeseries.",
  "unit": "",
  "source": "Office for National Statistics",
  "nationalStatistic": false,
  "years": [
    {
      "date": "1997",
      "value": "41820",
      "year": "1997",
      "sourceDataset": "UKEA"
    },
    {
      "date": "1998",
      "value": "45204",
      "year": "1998",
      "sourceDataset": "UKEA"
    },
    {
      "date": "1999",
      "value": "49824",
      "year": "1999",
      "sourceDataset": "UKEA"
    },
    {
      "date": "2000",
      "value": "54915",
      "year": "2000",
      "sourceDataset": "UKEA"
    },
    {
      "date": "2001",
      "value": "58022",
      "year": "2001",
      "sourceDataset": "UKEA"
    },
    {
      "date": "2002",
      "value": "61331",
      "year": "2002",
      "sourceDataset": "UKEA"
    },
    {
      "date": "2003",
      "value": "72532",
      "year": "2003",
      "sourceDataset": "UKEA"
    },
    {
      "date": "2004",
      "value": "81674",
      "year": "2004",
      "sourceDataset": "UKEA"
    },
    {
      "date": "2005",
      "value": "90982",
      "year": "2005",
      "sourceDataset": "UKEA"
    },
    {
      "date": "2006",
      "value": "102176",
      "year": "2006",
      "sourceDataset": "UKEA"
    },
    {
      "date": "2007",
      "value": "109482",
      "year": "2007",
      "sourceDataset": "UKEA"
    },
    {
      "date": "2008",
      "value": "106047",
      "year": "2008",
      "sourceDataset": "UKEA"
    },
    {
      "date": "2009",
      "value": "106772",
      "year": "2009",
      "sourceDataset": "UKEA"
    },
    {
      "date": "2010",
      "value": "121198",
      "year": "2010",
      "sourceDataset": "UKEA"
    },
    {
      "date": "2011",
      "value": "123512",
      "year": "2011",
      "sourceDataset": "UKEA"
    },
    {
      "date": "2012",
      "value": "128823",
      "year": "2012",
      "sourceDataset": "UKEA"
    },
    {
      "date": "2013",
      "value": "136765",
      "year": "2013",
      "sourceDataset": "UKEA"
    }
  ],
  "quarters": [
    {
      "date": "1997 Q1",
      "value": "10049",
      "year": "1997",
      "quarter": "Q1",
      "sourceDataset": "UKEA"
    },
    {
      "date": "1997 Q2",
      "value": "10279",
      "year": "1997",
      "quarter": "Q2",
      "sourceDataset": "UKEA"
    },
    {
      "date": "1997 Q3",
      "value": "10590",
      "year": "1997",
      "quarter": "Q3",
      "sourceDataset": "UKEA"
    },
    {
      "date": "1997 Q4",
      "value": "10902",
      "year": "1997",
      "quarter": "Q4",
      "sourceDataset": "UKEA"
    },
    {
      "date": "1998 Q1",
      "value": "10847",
      "year": "1998",
      "quarter": "Q1",
      "sourceDataset": "UKEA"
    },
    {
      "date": "1998 Q2",
      "value": "11248",
      "year": "1998",
      "quarter": "Q2",
      "sourceDataset": "UKEA"
    },
    {
      "date": "1998 Q3",
      "value": "11544",
      "year": "1998",
      "quarter": "Q3",
      "sourceDataset": "UKEA"
    },
    {
      "date": "1998 Q4",
      "value": "11565",
      "year": "1998",
      "quarter": "Q4",
      "sourceDataset": "UKEA"
    },
    {
      "date": "1999 Q1",
      "value": "12307",
      "year": "1999",
      "quarter": "Q1",
      "sourceDataset": "UKEA"
    },
    {
      "date": "1999 Q2",
      "value": "12114",
      "year": "1999",
      "quarter": "Q2",
      "sourceDataset": "UKEA"
    },
    {
      "date": "1999 Q3",
      "value": "12655",
      "year": "1999",
      "quarter": "Q3",
      "sourceDataset": "UKEA"
    },
    {
      "date": "1999 Q4",
      "value": "12748",
      "year": "1999",
      "quarter": "Q4",
      "sourceDataset": "UKEA"
    },
    {
      "date": "2000 Q1",
      "value": "13057",
      "year": "2000",
      "quarter": "Q1",
      "sourceDataset": "UKEA"
    },
    {
      "date": "2000 Q2",
      "value": "13559",
      "year": "2000",
      "quarter": "Q2",
      "sourceDataset": "UKEA"
    },
    {
      "date": "2000 Q3",
      "value": "13699",
      "year": "2000",
      "quarter": "Q3",
      "sourceDataset": "UKEA"
    },
    {
      "date": "2000 Q4",
      "value": "14600",
      "year": "2000",
      "quarter": "Q4",
      "sourceDataset": "UKEA"
    },
    {
      "date": "2001 Q1",
      "value": "15188",
      "year": "2001",
      "quarter": "Q1",
      "sourceDataset": "UKEA"
    },
    {
      "date": "2001 Q2",
      "value": "14116",
      "year": "2001",
      "quarter": "Q2",
      "sourceDataset": "UKEA"
    },
    {
      "date": "2001 Q3",
      "value": "14063",
      "year": "2001",
      "quarter": "Q3",
      "sourceDataset": "UKEA"
    },
    {
      "date": "2001 Q4",
      "value": "14655",
      "year": "2001",
      "quarter": "Q4",
      "sourceDataset": "UKEA"
    },
    {
      "date": "2002 Q1",
      "value": "15284",
      "year": "2002",
      "quarter": "Q1",
      "sourceDataset": "UKEA"
    },
    {
      "date": "2002 Q2",
      "value": "14893",
      "year": "2002",
      "quarter": "Q2",
      "sourceDataset": "UKEA"
    },
    {
      "date": "2002 Q3",
      "value": "15346",
      "year": "2002",
      "quarter": "Q3",
      "sourceDataset": "UKEA"
    },
    {
      "date": "2002 Q4",
      "value": "15808",
      "year": "2002",
      "quarter": "Q4",
      "sourceDataset": "UKEA"
    },
    {
      "date": "2003 Q1",
      "value": "16950",
      "year": "2003",
      "quarter": "Q1",
      "sourceDataset": "UKEA"
    },
    {
      "date": "2003 Q2",
      "value": "17370",
      "year": "2003",
      "quarter": "Q2",
      "sourceDataset": "UKEA"
    },
    {
      "date": "2003 Q3",
      "value": "18852",
      "year": "2003",
      "quarter": "Q3",
      "sourceDataset": "UKEA"
    },
    {
      "date": "2003 Q4",
      "value": "19360",
      "year": "2003",
      "quarter": "Q4",
      "sourceDataset": "UKEA"
    },
    {
      "date": "2004 Q1",
      "value": "20022",
      "year": "2004",
      "quarter": "Q1",
      "sourceDataset": "UKEA"
    },
    {
      "date": "2004 Q2",
      "value": "19686",
      "year": "2004",
      "quarter": "Q2",
      "sourceDataset": "UKEA"
    },
    {
      "date": "2004 Q3",
      "value": "20527",
      "year": "2004",
      "quarter": "Q3",
      "sourceDataset": "UKEA"
    },
    {
      "date": "2004 Q4",
      "value": "21439",
      "year": "2004",
      "quarter": "Q4",
      "sourceDataset": "UKEA"
    },
    {
      "date": "2005 Q1",
      "value": "22140",
      "year": "2005",
      "quarter": "Q1",
      "sourceDataset": "UKEA"
    },
    {
      "date": "2005 Q2",
      "value": "21861",
      "year": "2005",
      "quarter": "Q2",
      "sourceDataset": "UKEA"
    },
    {
      "date": "2005 Q3",
      "value": "22712",
      "year": "2005",
      "quarter": "Q3",
      "sourceDataset": "UKEA"
    },
    {
      "date": "2005 Q4",
      "value": "24269",
      "year": "2005",
      "quarter": "Q4",
      "sourceDataset": "UKEA"
    },
    {
      "date": "2006 Q1",
      "value": "24987",
      "year": "2006",
      "quarter": "Q1",
      "sourceDataset": "UKEA"
    },
    {
      "date": "2006 Q2",
      "value": "23738",
      "year": "2006",
      "quarter": "Q2",
      "sourceDataset": "UKEA"
    },
    {
      "date": "2006 Q3",
      "value": "25333",
      "year": "2006",
      "quarter": "Q3",
      "sourceDataset": "UKEA"
    },
    {
      "date": "2006 Q4",
      "value": "28118",
      "year": "2006",
      "quarter": "Q4",
      "sourceDataset": "UKEA"
    },
    {
      "date": "2007 Q1",
      "value": "26119",
      "year": "2007",
      "quarter": "Q1",
      "sourceDataset": "UKEA"
    },
    {
      "date": "2007 Q2",
      "value": "27850",
      "year": "2007",
      "quarter": "Q2",
      "sourceDataset": "UKEA"
    },
    {
      "date": "2007 Q3",
      "value": "28140",
      "year": "2007",
      "quarter": "Q3",
      "sourceDataset": "UKEA"
    },
    {
      "date": "2007 Q4",
      "value": "27373",
      "year": "2007",
      "quarter": "Q4",
      "sourceDataset": "UKEA"
    },
    {
      "date": "2008 Q1",
      "value": "28411",
      "year": "2008",
      "quarter": "Q1",
      "sourceDataset": "UKEA"
    },
    {
      "date": "2008 Q2",
      "value": "26524",
      "year": "2008",
      "quarter": "Q2",
      "sourceDataset": "UKEA"
    },
    {
      "date": "2008 Q3",
      "value": "25956",
      "year": "2008",
      "quarter": "Q3",
      "sourceDataset": "UKEA"
    },
    {
      "date": "2008 Q4",
      "value": "25156",
      "year": "2008",
      "quarter": "Q4",
      "sourceDataset": "UKEA"
    },
    {
      "date": "2009 Q1",
      "value": "26699",
      "year": "2009",
      "quarter": "Q1",
      "sourceDataset": "UKEA"
    },
    {
      "date": "2009 Q2",
      "value": "25373",
      "year": "2009",
      "quarter": "Q2",
      "sourceDataset": "UKEA"
    },
    {
      "date": "2009 Q3",
      "value": "25559",
      "year": "2009",
      "quarter": "Q3",
      "sourceDataset": "UKEA"
    },
    {
      "date": "2009 Q4",
      "value": "29141",
      "year": "2009",
      "quarter": "Q4",
      "sourceDataset": "UKEA"
    },
    {
      "date": "2010 Q1",
      "value": "30272",
      "year": "2010",
      "quarter": "Q1",
      "sourceDataset": "UKEA"
    },
    {
      "date": "2010 Q2",
      "value": "30558",
      "year": "2010",
      "quarter": "Q2",
      "sourceDataset": "UKEA"
    },
    {
      "date": "2010 Q3",
      "value": "30042",
      "year": "2010",
      "quarter": "Q3",
      "sourceDataset": "UKEA"
    },
    {
      "date": "2010 Q4",
      "value": "30326",
      "year": "2010",
      "quarter": "Q4",
      "sourceDataset": "UKEA"
    },
    {
      "date": "2011 Q1",
      "value": "30772",
      "year": "2011",
      "quarter": "Q1",
      "sourceDataset": "UKEA"
    },
    {
      "date": "2011 Q2",
      "value": "30280",
      "year": "2011",
      "quarter": "Q2",
      "sourceDataset": "UKEA"
    },
    {
      "date": "2011 Q3",
      "value": "30224",
      "year": "2011",
      "quarter": "Q3",
      "sourceDataset": "UKEA"
    },
    {
      "date": "2011 Q4",
      "value": "32236",
      "year": "2011",
      "quarter": "Q4",
      "sourceDataset": "UKEA"
    },
    {
      "date": "2012 Q1",
      "value": "34234",
      "year": "2012",
      "quarter": "Q1",
      "sourceDataset": "UKEA"
    },
    {
      "date": "2012 Q2",
      "value": "30808",
      "year": "2012",
      "quarter": "Q2",
      "sourceDataset": "UKEA"
    },
    {
      "date": "2012 Q3",
      "value": "32644",
      "year": "2012",
      "quarter": "Q3",
      "sourceDataset": "UKEA"
    },
    {
      "date": "2012 Q4",
      "value": "31137",
      "year": "2012",
      "quarter": "Q4",
      "sourceDataset": "UKEA"
    },
    {
      "date": "2013 Q1",
      "value": "32891",
      "year": "2013",
      "quarter": "Q1",
      "sourceDataset": "UKEA"
    },
    {
      "date": "2013 Q2",
      "value": "34345",
      "year": "2013",
      "quarter": "Q2",
      "sourceDataset": "UKEA"
    },
    {
      "date": "2013 Q3",
      "value": "35278",
      "year": "2013",
      "quarter": "Q3",
      "sourceDataset": "UKEA"
    },
    {
      "date": "2013 Q4",
      "value": "34251",
      "year": "2013",
      "quarter": "Q4",
      "sourceDataset": "UKEA"
    },
    {
      "date": "2014 Q1",
      "value": "33077",
      "year": "2014",
      "quarter": "Q1",
      "sourceDataset": "UKEA"
    },
    {
      "date": "2014 Q2",
      "value": "32827",
      "year": "2014",
      "quarter": "Q2",
      "sourceDataset": "UKEA"
    }
  ],
  "months": [],
  "relatedBulletins": [
    "/economy/grossdomesticproductgdp/bulletins/gdppreliminaryestimateq32014"
  ],
  "relatedTimeseries": [],
  "sourceDatasets": [
    "UKEA"
  ],
  "type": "timeseries",
  "name": "People not in Work",
  "uri": "/economy/grossdomesticproductgdp/timeseries/l8ni",
  "fileName": "l8ni",
  "breadcrumb": [
    {
      "index": 0,
      "type": "home",
      "name": "Economy",
      "fileName": "economy"
    },
    {
      "index": 0,
      "type": "home",
      "name": "Gross Domestic Product (GDP)",
      "fileName": "grossdomesticproductgdp",
      "breadcrumb": []
    }
  ]
}