{
  "cdid": "ZAUR",
  "note1": "This content is not available in the prototype but in future will provide a note about this timeseries.",
  "note2": "This content is not available in the prototype but in future will provide a note about this timeseries.",
  "unit": "",
  "source": "Office for National Statistics",
  "nationalStatistic": false,
  "years": [
    {
      "date": "1979",
      "value": "15948",
      "year": "1979",
      "sourceDataset": "PB"
    },
    {
      "date": "1980",
      "value": "15651",
      "year": "1980",
      "sourceDataset": "PB"
    },
    {
      "date": "1981",
      "value": "20909",
      "year": "1981",
      "sourceDataset": "PB"
    },
    {
      "date": "1982",
      "value": "23848",
      "year": "1982",
      "sourceDataset": "PB"
    },
    {
      "date": "1983",
      "value": "22097",
      "year": "1983",
      "sourceDataset": "PB"
    },
    {
      "date": "1984",
      "value": "26633",
      "year": "1984",
      "sourceDataset": "PB"
    },
    {
      "date": "1985",
      "value": "29197",
      "year": "1985",
      "sourceDataset": "PB"
    },
    {
      "date": "1986",
      "value": "31592",
      "year": "1986",
      "sourceDataset": "PB"
    },
    {
      "date": "1987",
      "value": "33410",
      "year": "1987",
      "sourceDataset": "PB"
    },
    {
      "date": "1988",
      "value": "46192",
      "year": "1988",
      "sourceDataset": "PB"
    },
    {
      "date": "1989",
      "value": "66858",
      "year": "1989",
      "sourceDataset": "PB"
    },
    {
      "date": "1990",
      "value": "86243",
      "year": "1990",
      "sourceDataset": "PB"
    },
    {
      "date": "1991",
      "value": "118906",
      "year": "1991",
      "sourceDataset": "PB"
    },
    {
      "date": "1992",
      "value": "160414",
      "year": "1992",
      "sourceDataset": "PB"
    },
    {
      "date": "1993",
      "value": "261931",
      "year": "1993",
      "sourceDataset": "PB"
    },
    {
      "date": "1994",
      "value": "223921",
      "year": "1994",
      "sourceDataset": "PB"
    },
    {
      "date": "1995",
      "value": "281503",
      "year": "1995",
      "sourceDataset": "PB"
    },
    {
      "date": "1996",
      "value": "350184",
      "year": "1996",
      "sourceDataset": "PB"
    },
    {
      "date": "1997",
      "value": "398600",
      "year": "1997",
      "sourceDataset": "PB"
    },
    {
      "date": "1998",
      "value": "413012",
      "year": "1998",
      "sourceDataset": "PB"
    },
    {
      "date": "1999",
      "value": "487586",
      "year": "1999",
      "sourceDataset": "PB"
    },
    {
      "date": "2000",
      "value": "519899",
      "year": "2000",
      "sourceDataset": "PB"
    },
    {
      "date": "2001",
      "value": "631017",
      "year": "2001",
      "sourceDataset": "PB"
    },
    {
      "date": "2002",
      "value": "639379",
      "year": "2002",
      "sourceDataset": "PB"
    },
    {
      "date": "2003",
      "value": "716739",
      "year": "2003",
      "sourceDataset": "PB"
    },
    {
      "date": "2004",
      "value": "854390",
      "year": "2004",
      "sourceDataset": "PB"
    },
    {
      "date": "2005",
      "value": "1090268",
      "year": "2005",
      "sourceDataset": "PB"
    },
    {
      "date": "2006",
      "value": "1098009",
      "year": "2006",
      "sourceDataset": "PB"
    },
    {
      "date": "2007",
      "value": "1218555",
      "year": "2007",
      "sourceDataset": "PB"
    },
    {
      "date": "2008",
      "value": "1262874",
      "year": "2008",
      "sourceDataset": "PB"
    },
    {
      "date": "2009",
      "value": "1219861",
      "year": "2009",
      "sourceDataset": "PB"
    },
    {
      "date": "2010",
      "value": "1378786",
      "year": "2010",
      "sourceDataset": "PB"
    },
    {
      "date": "2011",
      "value": "1485496",
      "year": "2011",
      "sourceDataset": "PB"
    },
    {
      "date": "2012",
      "value": "1615950",
      "year": "2012",
      "sourceDataset": "PB"
    },
    {
      "date": "2013",
      "value": "1721031",
      "year": "2013",
      "sourceDataset": "UKEA"
    }
  ],
  "quarters": [
    {
      "date": "1997 Q1",
      "value": "379045",
      "year": "1997",
      "quarter": "Q1",
      "sourceDataset": "UKEA"
    },
    {
      "date": "1997 Q2",
      "value": "423267",
      "year": "1997",
      "quarter": "Q2",
      "sourceDataset": "UKEA"
    },
    {
      "date": "1997 Q3",
      "value": "440064",
      "year": "1997",
      "quarter": "Q3",
      "sourceDataset": "UKEA"
    },
    {
      "date": "1997 Q4",
      "value": "414114",
      "year": "1997",
      "quarter": "Q4",
      "sourceDataset": "UKEA"
    },
    {
      "date": "1998 Q1",
      "value": "420855",
      "year": "1998",
      "quarter": "Q1",
      "sourceDataset": "UKEA"
    },
    {
      "date": "1998 Q2",
      "value": "438884",
      "year": "1998",
      "quarter": "Q2",
      "sourceDataset": "UKEA"
    },
    {
      "date": "1998 Q3",
      "value": "414497",
      "year": "1998",
      "quarter": "Q3",
      "sourceDataset": "UKEA"
    },
    {
      "date": "1998 Q4",
      "value": "429893",
      "year": "1998",
      "quarter": "Q4",
      "sourceDataset": "UKEA"
    },
    {
      "date": "1999 Q1",
      "value": "489653",
      "year": "1999",
      "quarter": "Q1",
      "sourceDataset": "UKEA"
    },
    {
      "date": "1999 Q2",
      "value": "505935",
      "year": "1999",
      "quarter": "Q2",
      "sourceDataset": "UKEA"
    },
    {
      "date": "1999 Q3",
      "value": "502752",
      "year": "1999",
      "quarter": "Q3",
      "sourceDataset": "UKEA"
    },
    {
      "date": "1999 Q4",
      "value": "500124",
      "year": "1999",
      "quarter": "Q4",
      "sourceDataset": "UKEA"
    },
    {
      "date": "2000 Q1",
      "value": "507776",
      "year": "2000",
      "quarter": "Q1",
      "sourceDataset": "UKEA"
    },
    {
      "date": "2000 Q2",
      "value": "559495",
      "year": "2000",
      "quarter": "Q2",
      "sourceDataset": "UKEA"
    },
    {
      "date": "2000 Q3",
      "value": "551584",
      "year": "2000",
      "quarter": "Q3",
      "sourceDataset": "UKEA"
    },
    {
      "date": "2000 Q4",
      "value": "532639",
      "year": "2000",
      "quarter": "Q4",
      "sourceDataset": "UKEA"
    },
    {
      "date": "2001 Q1",
      "value": "635425",
      "year": "2001",
      "quarter": "Q1",
      "sourceDataset": "UKEA"
    },
    {
      "date": "2001 Q2",
      "value": "652508",
      "year": "2001",
      "quarter": "Q2",
      "sourceDataset": "UKEA"
    },
    {
      "date": "2001 Q3",
      "value": "636646",
      "year": "2001",
      "quarter": "Q3",
      "sourceDataset": "UKEA"
    },
    {
      "date": "2001 Q4",
      "value": "655838",
      "year": "2001",
      "quarter": "Q4",
      "sourceDataset": "UKEA"
    },
    {
      "date": "2002 Q1",
      "value": "709096",
      "year": "2002",
      "quarter": "Q1",
      "sourceDataset": "UKEA"
    },
    {
      "date": "2002 Q2",
      "value": "731938",
      "year": "2002",
      "quarter": "Q2",
      "sourceDataset": "UKEA"
    },
    {
      "date": "2002 Q3",
      "value": "699101",
      "year": "2002",
      "quarter": "Q3",
      "sourceDataset": "UKEA"
    },
    {
      "date": "2002 Q4",
      "value": "670172",
      "year": "2002",
      "quarter": "Q4",
      "sourceDataset": "UKEA"
    },
    {
      "date": "2003 Q1",
      "value": "727728",
      "year": "2003",
      "quarter": "Q1",
      "sourceDataset": "UKEA"
    },
    {
      "date": "2003 Q2",
      "value": "747357",
      "year": "2003",
      "quarter": "Q2",
      "sourceDataset": "UKEA"
    },
    {
      "date": "2003 Q3",
      "value": "800020",
      "year": "2003",
      "quarter": "Q3",
      "sourceDataset": "UKEA"
    },
    {
      "date": "2003 Q4",
      "value": "739253",
      "year": "2003",
      "quarter": "Q4",
      "sourceDataset": "UKEA"
    },
    {
      "date": "2004 Q1",
      "value": "794263",
      "year": "2004",
      "quarter": "Q1",
      "sourceDataset": "UKEA"
    },
    {
      "date": "2004 Q2",
      "value": "832847",
      "year": "2004",
      "quarter": "Q2",
      "sourceDataset": "UKEA"
    },
    {
      "date": "2004 Q3",
      "value": "885362",
      "year": "2004",
      "quarter": "Q3",
      "sourceDataset": "UKEA"
    },
    {
      "date": "2004 Q4",
      "value": "899784",
      "year": "2004",
      "quarter": "Q4",
      "sourceDataset": "UKEA"
    },
    {
      "date": "2005 Q1",
      "value": "978304",
      "year": "2005",
      "quarter": "Q1",
      "sourceDataset": "UKEA"
    },
    {
      "date": "2005 Q2",
      "value": "1037538",
      "year": "2005",
      "quarter": "Q2",
      "sourceDataset": "UKEA"
    },
    {
      "date": "2005 Q3",
      "value": "1091299",
      "year": "2005",
      "quarter": "Q3",
      "sourceDataset": "UKEA"
    },
    {
      "date": "2005 Q4",
      "value": "1119104",
      "year": "2005",
      "quarter": "Q4",
      "sourceDataset": "UKEA"
    },
    {
      "date": "2006 Q1",
      "value": "1186865",
      "year": "2006",
      "quarter": "Q1",
      "sourceDataset": "UKEA"
    },
    {
      "date": "2006 Q2",
      "value": "1128242",
      "year": "2006",
      "quarter": "Q2",
      "sourceDataset": "UKEA"
    },
    {
      "date": "2006 Q3",
      "value": "1115972",
      "year": "2006",
      "quarter": "Q3",
      "sourceDataset": "UKEA"
    },
    {
      "date": "2006 Q4",
      "value": "1130465",
      "year": "2006",
      "quarter": "Q4",
      "sourceDataset": "UKEA"
    },
    {
      "date": "2007 Q1",
      "value": "1192373",
      "year": "2007",
      "quarter": "Q1",
      "sourceDataset": "UKEA"
    },
    {
      "date": "2007 Q2",
      "value": "1243158",
      "year": "2007",
      "quarter": "Q2",
      "sourceDataset": "UKEA"
    },
    {
      "date": "2007 Q3",
      "value": "1259194",
      "year": "2007",
      "quarter": "Q3",
      "sourceDataset": "UKEA"
    },
    {
      "date": "2007 Q4",
      "value": "1240719",
      "year": "2007",
      "quarter": "Q4",
      "sourceDataset": "UKEA"
    },
    {
      "date": "2008 Q1",
      "value": "1374263",
      "year": "2008",
      "quarter": "Q1",
      "sourceDataset": "UKEA"
    },
    {
      "date": "2008 Q2",
      "value": "1310940",
      "year": "2008",
      "quarter": "Q2",
      "sourceDataset": "UKEA"
    },
    {
      "date": "2008 Q3",
      "value": "1241040",
      "year": "2008",
      "quarter": "Q3",
      "sourceDataset": "UKEA"
    },
    {
      "date": "2008 Q4",
      "value": "1304404",
      "year": "2008",
      "quarter": "Q4",
      "sourceDataset": "UKEA"
    },
    {
      "date": "2009 Q1",
      "value": "1239369",
      "year": "2009",
      "quarter": "Q1",
      "sourceDataset": "UKEA"
    },
    {
      "date": "2009 Q2",
      "value": "1265717",
      "year": "2009",
      "quarter": "Q2",
      "sourceDataset": "UKEA"
    },
    {
      "date": "2009 Q3",
      "value": "1383565",
      "year": "2009",
      "quarter": "Q3",
      "sourceDataset": "UKEA"
    },
    {
      "date": "2009 Q4",
      "value": "1303966",
      "year": "2009",
      "quarter": "Q4",
      "sourceDataset": "UKEA"
    },
    {
      "date": "2010 Q1",
      "value": "1352206",
      "year": "2010",
      "quarter": "Q1",
      "sourceDataset": "UKEA"
    },
    {
      "date": "2010 Q2",
      "value": "1467553",
      "year": "2010",
      "quarter": "Q2",
      "sourceDataset": "UKEA"
    },
    {
      "date": "2010 Q3",
      "value": "1607192",
      "year": "2010",
      "quarter": "Q3",
      "sourceDataset": "UKEA"
    },
    {
      "date": "2010 Q4",
      "value": "1483599",
      "year": "2010",
      "quarter": "Q4",
      "sourceDataset": "UKEA"
    },
    {
      "date": "2011 Q1",
      "value": "1584952",
      "year": "2011",
      "quarter": "Q1",
      "sourceDataset": "UKEA"
    },
    {
      "date": "2011 Q2",
      "value": "1609873",
      "year": "2011",
      "quarter": "Q2",
      "sourceDataset": "UKEA"
    },
    {
      "date": "2011 Q3",
      "value": "1677823",
      "year": "2011",
      "quarter": "Q3",
      "sourceDataset": "UKEA"
    },
    {
      "date": "2011 Q4",
      "value": "1603752",
      "year": "2011",
      "quarter": "Q4",
      "sourceDataset": "UKEA"
    },
    {
      "date": "2012 Q1",
      "value": "1587156",
      "year": "2012",
      "quarter": "Q1",
      "sourceDataset": "UKEA"
    },
    {
      "date": "2012 Q2",
      "value": "1667906",
      "year": "2012",
      "quarter": "Q2",
      "sourceDataset": "UKEA"
    },
    {
      "date": "2012 Q3",
      "value": "1732905",
      "year": "2012",
      "quarter": "Q3",
      "sourceDataset": "UKEA"
    },
    {
      "date": "2012 Q4",
      "value": "1719879",
      "year": "2012",
      "quarter": "Q4",
      "sourceDataset": "UKEA"
    },
    {
      "date": "2013 Q1",
      "value": "1749000",
      "year": "2013",
      "quarter": "Q1",
      "sourceDataset": "UKEA"
    },
    {
      "date": "2013 Q2",
      "value": "1840601",
      "year": "2013",
      "quarter": "Q2",
      "sourceDataset": "UKEA"
    },
    {
      "date": "2013 Q3",
      "value": "1718221",
      "year": "2013",
      "quarter": "Q3",
      "sourceDataset": "UKEA"
    },
    {
      "date": "2013 Q4",
      "value": "1721031",
      "year": "2013",
      "quarter": "Q4",
      "sourceDataset": "UKEA"
    },
    {
      "date": "2014 Q1",
      "value": "1761985",
      "year": "2014",
      "quarter": "Q1",
      "sourceDataset": "UKEA"
    },
    {
      "date": "2014 Q2",
      "value": "1738675",
      "year": "2014",
      "quarter": "Q2",
      "sourceDataset": "UKEA"
    }
  ],
  "months": [],
  "relatedBulletins": [
    "/economy/nationalaccounts/bulletins/balanceofpaymentsq12014"
  ],
  "relatedTimeseries": [],
  "sourceDatasets": [
    "PB",
    "UKEA"
  ],
  "type": "timeseries",
  "name": "IMF BoP IIP external debt Total other sectors liabilities (incl non-bk FCs, NCF",
  "uri": "/economy/nationalaccounts/timeseries/zaur",
  "fileName": "zaur",
  "breadcrumb": [
    {
      "index": 0,
      "type": "home",
      "name": "Economy",
      "fileName": "economy"
    },
    {
      "index": 0,
      "type": "home",
      "name": "National Accounts",
      "fileName": "nationalaccounts",
      "breadcrumb": []
    }
  ]
}