{
  "cdid": "RLLA",
  "note1": "Lorem ipsum dolor sit amet, consectetur adipiscing elit. Praesent quam leo, blandit a turpis non, varius feugiat mi. Lorem ipsum dolor sit amet, consectetur adipiscing elit. In posuere lectus eu laoreet ultrices. Donec ac sodales libero, eget fermentum arcu.",
  "note2": "Fusce pharetra, libero in imperdiet ultricies, ex erat tempor dolor, vitae aliquet magna velit in urna. Duis finibus augue velit, ut consectetur risus imperdiet in. Sed tempus congue ante, ac cursus diam porttitor vitae. Vivamus arcu leo, volutpat in mauris ac, lacinia fermentum velit. Sed dictum tortor justo, aliquet facilisis lorem dictum a.",
  "data": [
    {
      "date": "1987",
      "value": "584"
    },
    {
      "date": "1988",
      "value": "323"
    },
    {
      "date": "1989",
      "value": "1029"
    },
    {
      "date": "1990",
      "value": "-731"
    },
    {
      "date": "1991",
      "value": "857"
    },
    {
      "date": "1992",
      "value": "-12"
    },
    {
      "date": "1993",
      "value": "-249"
    },
    {
      "date": "1994",
      "value": "838"
    },
    {
      "date": "1995",
      "value": "-422"
    },
    {
      "date": "1996",
      "value": "961"
    },
    {
      "date": "1997",
      "value": "49"
    },
    {
      "date": "1998",
      "value": "-239"
    },
    {
      "date": "1999",
      "value": "4817"
    },
    {
      "date": "2000",
      "value": "190"
    },
    {
      "date": "2001",
      "value": "9527"
    },
    {
      "date": "2002",
      "value": "371"
    },
    {
      "date": "2003",
      "value": "4357"
    },
    {
      "date": "2004",
      "value": "-560"
    },
    {
      "date": "2005",
      "value": "3003"
    },
    {
      "date": "2006",
      "value": "2131"
    },
    {
      "date": "2007",
      "value": "-2473"
    },
    {
      "date": "2008",
      "value": "-4563"
    },
    {
      "date": "2009",
      "value": "-2659"
    },
    {
      "date": "2010",
      "value": "2322"
    },
    {
      "date": "2011",
      "value": "-1757"
    },
    {
      "date": "2012",
      "value": "2363"
    },
    {
      "date": "2013",
      "value": "3371"
    },
    {
      "date": "1987 Q1",
      "value": "-156"
    },
    {
      "date": "1987 Q2",
      "value": "266"
    },
    {
      "date": "1987 Q3",
      "value": "284"
    },
    {
      "date": "1987 Q4",
      "value": "190"
    },
    {
      "date": "1988 Q1",
      "value": "-377"
    },
    {
      "date": "1988 Q2",
      "value": "411"
    },
    {
      "date": "1988 Q3",
      "value": "303"
    },
    {
      "date": "1988 Q4",
      "value": "-14"
    },
    {
      "date": "1989 Q1",
      "value": "820"
    },
    {
      "date": "1989 Q2",
      "value": "546"
    },
    {
      "date": "1989 Q3",
      "value": "263"
    },
    {
      "date": "1989 Q4",
      "value": "-600"
    },
    {
      "date": "1990 Q1",
      "value": "-372"
    },
    {
      "date": "1990 Q2",
      "value": "838"
    },
    {
      "date": "1990 Q3",
      "value": "-795"
    },
    {
      "date": "1990 Q4",
      "value": "-402"
    },
    {
      "date": "1991 Q1",
      "value": "532"
    },
    {
      "date": "1991 Q2",
      "value": "-210"
    },
    {
      "date": "1991 Q3",
      "value": "1056"
    },
    {
      "date": "1991 Q4",
      "value": "-521"
    },
    {
      "date": "1992 Q1",
      "value": "-664"
    },
    {
      "date": "1992 Q2",
      "value": "1050"
    },
    {
      "date": "1992 Q3",
      "value": "141"
    },
    {
      "date": "1992 Q4",
      "value": "-539"
    },
    {
      "date": "1993 Q1",
      "value": "55"
    },
    {
      "date": "1993 Q2",
      "value": "-289"
    },
    {
      "date": "1993 Q3",
      "value": "-103"
    },
    {
      "date": "1993 Q4",
      "value": "88"
    },
    {
      "date": "1994 Q1",
      "value": "732"
    },
    {
      "date": "1994 Q2",
      "value": "-255"
    },
    {
      "date": "1994 Q3",
      "value": "277"
    },
    {
      "date": "1994 Q4",
      "value": "84"
    },
    {
      "date": "1995 Q1",
      "value": "-60"
    },
    {
      "date": "1995 Q2",
      "value": "-220"
    },
    {
      "date": "1995 Q3",
      "value": "115"
    },
    {
      "date": "1995 Q4",
      "value": "-257"
    },
    {
      "date": "1996 Q1",
      "value": "1099"
    },
    {
      "date": "1996 Q2",
      "value": "-370"
    },
    {
      "date": "1996 Q3",
      "value": "29"
    },
    {
      "date": "1996 Q4",
      "value": "203"
    },
    {
      "date": "1997 Q1",
      "value": "277"
    },
    {
      "date": "1997 Q2",
      "value": "-665"
    },
    {
      "date": "1997 Q3",
      "value": "775"
    },
    {
      "date": "1997 Q4",
      "value": "-338"
    },
    {
      "date": "1998 Q1",
      "value": "1042"
    },
    {
      "date": "1998 Q2",
      "value": "2145"
    },
    {
      "date": "1998 Q3",
      "value": "-2475"
    },
    {
      "date": "1998 Q4",
      "value": "-951"
    },
    {
      "date": "1999 Q1",
      "value": "365"
    },
    {
      "date": "1999 Q2",
      "value": "2035"
    },
    {
      "date": "1999 Q3",
      "value": "1009"
    },
    {
      "date": "1999 Q4",
      "value": "1408"
    },
    {
      "date": "2000 Q1",
      "value": "-345"
    },
    {
      "date": "2000 Q2",
      "value": "1019"
    },
    {
      "date": "2000 Q3",
      "value": "696"
    },
    {
      "date": "2000 Q4",
      "value": "-1180"
    },
    {
      "date": "2001 Q1",
      "value": "8439"
    },
    {
      "date": "2001 Q2",
      "value": "38"
    },
    {
      "date": "2001 Q3",
      "value": "-1487"
    },
    {
      "date": "2001 Q4",
      "value": "2537"
    },
    {
      "date": "2002 Q1",
      "value": "-5299"
    },
    {
      "date": "2002 Q2",
      "value": "1874"
    },
    {
      "date": "2002 Q3",
      "value": "3052"
    },
    {
      "date": "2002 Q4",
      "value": "744"
    },
    {
      "date": "2003 Q1",
      "value": "1442"
    },
    {
      "date": "2003 Q2",
      "value": "510"
    },
    {
      "date": "2003 Q3",
      "value": "3643"
    },
    {
      "date": "2003 Q4",
      "value": "-1238"
    },
    {
      "date": "2004 Q1",
      "value": "-254"
    },
    {
      "date": "2004 Q2",
      "value": "516"
    },
    {
      "date": "2004 Q3",
      "value": "-386"
    },
    {
      "date": "2004 Q4",
      "value": "-436"
    },
    {
      "date": "2005 Q1",
      "value": "473"
    },
    {
      "date": "2005 Q2",
      "value": "-1135"
    },
    {
      "date": "2005 Q3",
      "value": "1759"
    },
    {
      "date": "2005 Q4",
      "value": "1906"
    },
    {
      "date": "2006 Q1",
      "value": "3778"
    },
    {
      "date": "2006 Q2",
      "value": "-3207"
    },
    {
      "date": "2006 Q3",
      "value": "730"
    },
    {
      "date": "2006 Q4",
      "value": "830"
    },
    {
      "date": "2007 Q1",
      "value": "-1885"
    },
    {
      "date": "2007 Q2",
      "value": "-1231"
    },
    {
      "date": "2007 Q3",
      "value": "979"
    },
    {
      "date": "2007 Q4",
      "value": "-336"
    },
    {
      "date": "2008 Q1",
      "value": "-5411"
    },
    {
      "date": "2008 Q2",
      "value": "449"
    },
    {
      "date": "2008 Q3",
      "value": "-2630"
    },
    {
      "date": "2008 Q4",
      "value": "3029"
    },
    {
      "date": "2009 Q1",
      "value": "-2145"
    },
    {
      "date": "2009 Q2",
      "value": "151"
    },
    {
      "date": "2009 Q3",
      "value": "372"
    },
    {
      "date": "2009 Q4",
      "value": "-1037"
    },
    {
      "date": "2010 Q1",
      "value": "479"
    },
    {
      "date": "2010 Q2",
      "value": "-1566"
    },
    {
      "date": "2010 Q3",
      "value": "1979"
    },
    {
      "date": "2010 Q4",
      "value": "1430"
    },
    {
      "date": "2011 Q1",
      "value": "4493"
    },
    {
      "date": "2011 Q2",
      "value": "-93"
    },
    {
      "date": "2011 Q3",
      "value": "-1835"
    },
    {
      "date": "2011 Q4",
      "value": "-4322"
    },
    {
      "date": "2012 Q1",
      "value": "1648"
    },
    {
      "date": "2012 Q2",
      "value": "1289"
    },
    {
      "date": "2012 Q3",
      "value": "-516"
    },
    {
      "date": "2012 Q4",
      "value": "-58"
    },
    {
      "date": "2013 Q1",
      "value": "4601"
    },
    {
      "date": "2013 Q2",
      "value": "-1116"
    },
    {
      "date": "2013 Q3",
      "value": "1342"
    },
    {
      "date": "2013 Q4",
      "value": "-1456"
    },
    {
      "date": "2014 Q1",
      "value": "-820"
    },
    {
      "date": "2014 Q2",
      "value": "152"
    }
  ],
  "uri": "/economy/investmentspensionsandtrusts/timeseries/rlla",
  "type": "timeseries",
  "name": "IIPT: COM: NET: Other UK liabilities",
  "fileName": "rlla",
  "breadcrumb": [
    {
      "index": 0,
      "type": "home",
      "name": "Employment and Labour Market",
      "fileName": "employmentandlabourmarket"
    },
    {
      "index": 0,
      "type": "home",
      "name": "People in Work",
      "fileName": "peopleinwork"
    },
    {
      "index": 0,
      "type": "home",
      "name": "Employment and Employee Types",
      "fileName": "employmentandemployeetypes",
      "breadcrumb": []
    }
  ]
}